[
  {
    "id": "65fce3bc22af84497fab05cbcff4b3c3",
    "time": "10:44 UTC",
    "timestamp": "2026-01-17T10:44:56.837120",
    "type": "WHALE ALERT",
    "message": "Large ASK order detected: $7,299 on 'No' at 0.99\u00a2",
    "severity": "medium",
    "market_question": "Will the US next strike Iran on January 30, 2026 (ET)?",
    "market_slug": "will-the-us-next-strike-iran-on-january-30-2026-et-866",
    "value": 7299.0812000000005,
    "price": 0.995,
    "size": 7335.76
  },
  {
    "id": "95352993917dc5c7b5495b1d42a39ae5",
    "time": "10:44 UTC",
    "timestamp": "2026-01-17T10:44:55.487823",
    "type": "WHALE ALERT",
    "message": "Large ASK order detected: $9,022 on 'No' at 0.99\u00a2",
    "severity": "medium",
    "market_question": "Will the US next strike Iran on January 18, 2026 (ET)?",
    "market_slug": "will-the-us-next-strike-iran-on-january-18-2026-et-229",
    "value": 9021.87,
    "price": 0.99,
    "size": 9113.0
  },
  {
    "id": "1cb25b90321f38ec5050c2f7692b82f8",
    "time": "10:44 UTC",
    "timestamp": "2026-01-17T10:44:55.486247",
    "type": "WHALE ALERT",
    "message": "Large BID order detected: $19,910 on 'No' at 0.98\u00a2",
    "severity": "medium",
    "market_question": "Will the US next strike Iran on January 18, 2026 (ET)?",
    "market_slug": "will-the-us-next-strike-iran-on-january-18-2026-et-229",
    "value": 19909.91335,
    "price": 0.985,
    "size": 20213.11
  },
  {
    "id": "7d83011966f66c0c2b3422c4e8a7b73d",
    "time": "10:44 UTC",
    "timestamp": "2026-01-17T10:44:54.576559",
    "type": "WHALE ALERT",
    "message": "Large ASK order detected: $10,578 on 'No' at 0.99\u00a2",
    "severity": "medium",
    "market_question": "Will the US next strike Iran on January 24, 2026 (ET)?",
    "market_slug": "will-the-us-next-strike-iran-on-january-24-2026-et-848",
    "value": 10577.92632,
    "price": 0.986,
    "size": 10728.12
  },
  {
    "id": "5fcce63c717c9e5a0acbe4d7d89e626e",
    "time": "10:44 UTC",
    "timestamp": "2026-01-17T10:44:54.068246",
    "type": "WHALE ALERT",
    "message": "Large ASK order detected: $8,280 on 'No' at 0.99\u00a2",
    "severity": "medium",
    "market_question": "Will the US next strike Iran on January 21, 2026 (ET)?",
    "market_slug": "will-the-us-next-strike-iran-on-january-21-2026-et-774",
    "value": 8279.9843,
    "price": 0.986,
    "size": 8397.55
  },
  {
    "id": "f690c8158a6925ad6d667176084601f7",
    "time": "10:44 UTC",
    "timestamp": "2026-01-17T10:44:53.578752",
    "type": "WHALE ALERT",
    "message": "Large ASK order detected: $6,614 on 'No' at 1.00\u00a2",
    "severity": "medium",
    "market_question": "Will the US next strike Iran on January 20, 2026 (ET)?",
    "market_slug": "will-the-us-next-strike-iran-on-january-20-2026-et-992",
    "value": 6614.31906,
    "price": 0.999,
    "size": 6620.94
  },
  {
    "id": "11c6bf2fef568f95bf9597d0092e9cdc",
    "time": "10:44 UTC",
    "timestamp": "2026-01-17T10:44:50.381408",
    "type": "WHALE ALERT",
    "message": "Large BID order detected: $5,104 on 'No' at 0.99\u00a2",
    "severity": "medium",
    "market_question": "Will the US next strike Iran on January 15, 2026 (ET)?",
    "market_slug": "will-the-us-next-strike-iran-on-january-15-2026-et-421",
    "value": 5104.09595,
    "price": 0.991,
    "size": 5150.45
  },
  {
    "id": "03ec596198647851a3db68b14f0a48c3",
    "time": "10:44 UTC",
    "timestamp": "2026-01-17T10:44:49.261774",
    "type": "WHALE ALERT",
    "message": "Large BID order detected: $6,683 on 'Yes' at 0.77\u00a2",
    "severity": "medium",
    "market_question": "Will the US not strike Iran by January 31, 2026?",
    "market_slug": "will-the-us-not-strike-iran-by-january-31-2026-314",
    "value": 6682.83,
    "price": 0.77,
    "size": 8679.0
  },
  {
    "id": "e3c733fcef71fd3fdb19aa20d4e97b00",
    "time": "10:44 UTC",
    "timestamp": "2026-01-17T10:44:48.052349",
    "type": "WHALE ALERT",
    "message": "Large ASK order detected: $108,765 on 'No' at 0.99\u00a2",
    "severity": "high",
    "market_question": "Will the US next strike Iran on January 17, 2026 (ET)?",
    "market_slug": "will-the-us-next-strike-iran-on-january-17-2026-et-219",
    "value": 108765.36989999999,
    "price": 0.99,
    "size": 109864.01
  },
  {
    "id": "3279c4f4e3ded07b87a3cd6884763c6c",
    "time": "10:44 UTC",
    "timestamp": "2026-01-17T10:44:45.641243",
    "type": "WHALE ALERT",
    "message": "Large ASK order detected: $20,228 on 'No' at 0.78\u00a2",
    "severity": "medium",
    "market_question": "Will the Seattle Seahawks win Super Bowl 2026?",
    "market_slug": "will-the-seattle-seahawks-win-super-bowl-2026",
    "value": 20227.5,
    "price": 0.775,
    "size": 26100.0
  },
  {
    "id": "3a3ab9585bf6d7673c4128a9955cd569",
    "time": "10:44 UTC",
    "timestamp": "2026-01-17T10:44:45.640237",
    "type": "WHALE ALERT",
    "message": "Large ASK order detected: $54,731 on 'No' at 0.78\u00a2",
    "severity": "high",
    "market_question": "Will the Seattle Seahawks win Super Bowl 2026?",
    "market_slug": "will-the-seattle-seahawks-win-super-bowl-2026",
    "value": 54731.28,
    "price": 0.776,
    "size": 70530.0
  },
  {
    "id": "d7418d1ab105cace9ad75aec64722e31",
    "time": "10:44 UTC",
    "timestamp": "2026-01-17T10:44:45.639227",
    "type": "WHALE ALERT",
    "message": "Large ASK order detected: $88,301 on 'No' at 0.79\u00a2",
    "severity": "high",
    "market_question": "Will the Seattle Seahawks win Super Bowl 2026?",
    "market_slug": "will-the-seattle-seahawks-win-super-bowl-2026",
    "value": 88301.40000000001,
    "price": 0.787,
    "size": 112200.0
  },
  {
    "id": "98e93abe8894a2591994b40c327bfe03",
    "time": "10:44 UTC",
    "timestamp": "2026-01-17T10:44:45.638087",
    "type": "WHALE ALERT",
    "message": "Large ASK order detected: $308,675 on 'No' at 1.00\u00a2",
    "severity": "high",
    "market_question": "Will the Seattle Seahawks win Super Bowl 2026?",
    "market_slug": "will-the-seattle-seahawks-win-super-bowl-2026",
    "value": 308674.62639,
    "price": 0.999,
    "size": 308983.61
  },
  {
    "id": "a4c1b7184d381131464fa8e4d005ac35",
    "time": "10:44 UTC",
    "timestamp": "2026-01-17T10:44:45.637046",
    "type": "WHALE ALERT",
    "message": "Large BID order detected: $7,147 on 'No' at 0.76\u00a2",
    "severity": "medium",
    "market_question": "Will the Seattle Seahawks win Super Bowl 2026?",
    "market_slug": "will-the-seattle-seahawks-win-super-bowl-2026",
    "value": 7147.20793,
    "price": 0.757,
    "size": 9441.49
  },
  {
    "id": "fdd15d108a1fc49132febe23beb82d8d",
    "time": "10:44 UTC",
    "timestamp": "2026-01-17T10:44:45.635853",
    "type": "WHALE ALERT",
    "message": "Large BID order detected: $70,806 on 'No' at 0.74\u00a2",
    "severity": "high",
    "market_question": "Will the Seattle Seahawks win Super Bowl 2026?",
    "market_slug": "will-the-seattle-seahawks-win-super-bowl-2026",
    "value": 70806.255,
    "price": 0.741,
    "size": 95555.0
  },
  {
    "id": "4707b916ff0b69dcf171fee8b95c16ab",
    "time": "10:44 UTC",
    "timestamp": "2026-01-17T10:44:45.463556",
    "type": "WHALE ALERT",
    "message": "Large ASK order detected: $24,749 on 'Yes' at 0.26\u00a2",
    "severity": "medium",
    "market_question": "Will the Seattle Seahawks win Super Bowl 2026?",
    "market_slug": "will-the-seattle-seahawks-win-super-bowl-2026",
    "value": 24748.745,
    "price": 0.259,
    "size": 95555.0
  },
  {
    "id": "549bcd701c0ec5963bd417f6be7b8867",
    "time": "10:44 UTC",
    "timestamp": "2026-01-17T10:44:45.462458",
    "type": "WHALE ALERT",
    "message": "Large BID order detected: $5,872 on 'Yes' at 0.23\u00a2",
    "severity": "medium",
    "market_question": "Will the Seattle Seahawks win Super Bowl 2026?",
    "market_slug": "will-the-seattle-seahawks-win-super-bowl-2026",
    "value": 5872.5,
    "price": 0.225,
    "size": 26100.0
  },
  {
    "id": "7364e00e12d9d6fc9a79f577fc74f903",
    "time": "10:44 UTC",
    "timestamp": "2026-01-17T10:44:45.461138",
    "type": "WHALE ALERT",
    "message": "Large BID order detected: $15,799 on 'Yes' at 0.22\u00a2",
    "severity": "medium",
    "market_question": "Will the Seattle Seahawks win Super Bowl 2026?",
    "market_slug": "will-the-seattle-seahawks-win-super-bowl-2026",
    "value": 15798.720000000001,
    "price": 0.224,
    "size": 70530.0
  },
  {
    "id": "ac960e1effbc2f4e51f6f785fd544b37",
    "time": "10:44 UTC",
    "timestamp": "2026-01-17T10:44:45.459980",
    "type": "WHALE ALERT",
    "message": "Large BID order detected: $23,899 on 'Yes' at 0.21\u00a2",
    "severity": "medium",
    "market_question": "Will the Seattle Seahawks win Super Bowl 2026?",
    "market_slug": "will-the-seattle-seahawks-win-super-bowl-2026",
    "value": 23898.6,
    "price": 0.213,
    "size": 112200.0
  },
  {
    "id": "3f3e5b40698b8a25f246575af0796349",
    "time": "10:44 UTC",
    "timestamp": "2026-01-17T10:44:45.193501",
    "type": "WHALE ALERT",
    "message": "Large ASK order detected: $35,888 on 'No' at 0.95\u00a2",
    "severity": "medium",
    "market_question": "Will the San Francisco 49ers win Super Bowl 2026?",
    "market_slug": "will-the-san-francisco-49ers-win-super-bowl-2026",
    "value": 35888.2315,
    "price": 0.955,
    "size": 37579.3
  },
  {
    "id": "2281276e3b0c0643951a35b6e197c656",
    "time": "10:44 UTC",
    "timestamp": "2026-01-17T10:44:45.192498",
    "type": "WHALE ALERT",
    "message": "Large ASK order detected: $12,572 on 'No' at 0.96\u00a2",
    "severity": "medium",
    "market_question": "Will the San Francisco 49ers win Super Bowl 2026?",
    "market_slug": "will-the-san-francisco-49ers-win-super-bowl-2026",
    "value": 12571.85706,
    "price": 0.959,
    "size": 13109.34
  },
  {
    "id": "2a0f156f7fa14b471d69df07b0280edb",
    "time": "10:44 UTC",
    "timestamp": "2026-01-17T10:44:45.191491",
    "type": "WHALE ALERT",
    "message": "Large ASK order detected: $46,248 on 'No' at 0.96\u00a2",
    "severity": "medium",
    "market_question": "Will the San Francisco 49ers win Super Bowl 2026?",
    "market_slug": "will-the-san-francisco-49ers-win-super-bowl-2026",
    "value": 46248.0,
    "price": 0.96,
    "size": 48175.0
  },
  {
    "id": "25062020631020b2f821ad65737ff8bd",
    "time": "10:44 UTC",
    "timestamp": "2026-01-17T10:44:45.190419",
    "type": "WHALE ALERT",
    "message": "Large ASK order detected: $31,200 on 'No' at 0.97\u00a2",
    "severity": "medium",
    "market_question": "Will the San Francisco 49ers win Super Bowl 2026?",
    "market_slug": "will-the-san-francisco-49ers-win-super-bowl-2026",
    "value": 31200.0,
    "price": 0.975,
    "size": 32000.0
  },
  {
    "id": "51f91b2c5c6779226a0a879ab95b5fb7",
    "time": "10:44 UTC",
    "timestamp": "2026-01-17T10:44:45.189386",
    "type": "WHALE ALERT",
    "message": "Large BID order detected: $7,946 on 'No' at 0.95\u00a2",
    "severity": "medium",
    "market_question": "Will the San Francisco 49ers win Super Bowl 2026?",
    "market_slug": "will-the-san-francisco-49ers-win-super-bowl-2026",
    "value": 7945.532669999999,
    "price": 0.953,
    "size": 8337.39
  },
  {
    "id": "9166a43880ff043db5cc30dea8d01e5c",
    "time": "10:44 UTC",
    "timestamp": "2026-01-17T10:44:45.188329",
    "type": "WHALE ALERT",
    "message": "Large BID order detected: $66,369 on 'No' at 0.94\u00a2",
    "severity": "high",
    "market_question": "Will the San Francisco 49ers win Super Bowl 2026?",
    "market_slug": "will-the-san-francisco-49ers-win-super-bowl-2026",
    "value": 66368.952,
    "price": 0.936,
    "size": 70907.0
  },
  {
    "id": "f522071a02101ee02b0f3adbcc07fbe3",
    "time": "10:44 UTC",
    "timestamp": "2026-01-17T10:44:45.187187",
    "type": "WHALE ALERT",
    "message": "Large BID order detected: $676,434 on 'No' at 0.93\u00a2",
    "severity": "high",
    "market_question": "Will the San Francisco 49ers win Super Bowl 2026?",
    "market_slug": "will-the-san-francisco-49ers-win-super-bowl-2026",
    "value": 676434.3300000001,
    "price": 0.933,
    "size": 725010.0
  },
  {
    "id": "dca4686d7273ff90249871ea2a28d6ea",
    "time": "10:44 UTC",
    "timestamp": "2026-01-17T10:44:44.986793",
    "type": "WHALE ALERT",
    "message": "Large ASK order detected: $48,576 on 'Yes' at 0.07\u00a2",
    "severity": "medium",
    "market_question": "Will the San Francisco 49ers win Super Bowl 2026?",
    "market_slug": "will-the-san-francisco-49ers-win-super-bowl-2026",
    "value": 48575.670000000006,
    "price": 0.067,
    "size": 725010.0
  },
  {
    "id": "8d5c2cd05fe42991163e08da3d505c97",
    "time": "10:44 UTC",
    "timestamp": "2026-01-17T10:44:42.390016",
    "type": "WHALE ALERT",
    "message": "Large ASK order detected: $13,912 on 'No' at 0.89\u00a2",
    "severity": "medium",
    "market_question": "Will the New England Patriots win Super Bowl 2026?",
    "market_slug": "will-the-new-england-patriots-win-super-bowl-2026",
    "value": 13912.2,
    "price": 0.885,
    "size": 15720.0
  },
  {
    "id": "1d973e344fdd48e87e08afdcf0d3028d",
    "time": "10:44 UTC",
    "timestamp": "2026-01-17T10:44:42.388947",
    "type": "WHALE ALERT",
    "message": "Large ASK order detected: $219,919 on 'No' at 0.89\u00a2",
    "severity": "high",
    "market_question": "Will the New England Patriots win Super Bowl 2026?",
    "market_slug": "will-the-new-england-patriots-win-super-bowl-2026",
    "value": 219919.0,
    "price": 0.89,
    "size": 247100.0
  },
  {
    "id": "1f8eb36c5d3321dac7046dfc5511e705",
    "time": "10:44 UTC",
    "timestamp": "2026-01-17T10:44:42.387766",
    "type": "WHALE ALERT",
    "message": "Large ASK order detected: $908,309 on 'No' at 1.00\u00a2",
    "severity": "high",
    "market_question": "Will the New England Patriots win Super Bowl 2026?",
    "market_slug": "will-the-new-england-patriots-win-super-bowl-2026",
    "value": 908309.07171,
    "price": 0.999,
    "size": 909218.29
  },
  {
    "id": "0cc7efaa237d6aae316a21444a275082",
    "time": "10:44 UTC",
    "timestamp": "2026-01-17T10:44:42.188532",
    "type": "WHALE ALERT",
    "message": "Large BID order detected: $27,181 on 'Yes' at 0.11\u00a2",
    "severity": "medium",
    "market_question": "Will the New England Patriots win Super Bowl 2026?",
    "market_slug": "will-the-new-england-patriots-win-super-bowl-2026",
    "value": 27181.0,
    "price": 0.11,
    "size": 247100.0
  },
  {
    "id": "0c7e25f8208278062b35ce0339018331",
    "time": "10:44 UTC",
    "timestamp": "2026-01-17T10:44:41.009729",
    "type": "WHALE ALERT",
    "message": "Large ASK order detected: $24,856 on 'No' at 0.80\u00a2",
    "severity": "medium",
    "market_question": "Will the Los Angeles Rams win Super Bowl 2026?",
    "market_slug": "will-the-los-angeles-rams-win-super-bowl-2026",
    "value": 24855.912,
    "price": 0.8,
    "size": 31069.89
  },
  {
    "id": "ccfd7d80c0a01eb9db32ae16edcc3c5f",
    "time": "10:44 UTC",
    "timestamp": "2026-01-17T10:44:41.008071",
    "type": "WHALE ALERT",
    "message": "Large ASK order detected: $49,013 on 'No' at 0.81\u00a2",
    "severity": "medium",
    "market_question": "Will the Los Angeles Rams win Super Bowl 2026?",
    "market_slug": "will-the-los-angeles-rams-win-super-bowl-2026",
    "value": 49012.86,
    "price": 0.806,
    "size": 60810.0
  },
  {
    "id": "459a34a9716723c823ff0ee450caaeea",
    "time": "10:44 UTC",
    "timestamp": "2026-01-17T10:44:41.006293",
    "type": "WHALE ALERT",
    "message": "Large ASK order detected: $891,699 on 'No' at 0.81\u00a2",
    "severity": "high",
    "market_question": "Will the Los Angeles Rams win Super Bowl 2026?",
    "market_slug": "will-the-los-angeles-rams-win-super-bowl-2026",
    "value": 891698.685,
    "price": 0.807,
    "size": 1104955.0
  },
  {
    "id": "5fe2b4aedeb9ef82a9735345cd29d5f8",
    "time": "10:44 UTC",
    "timestamp": "2026-01-17T10:44:41.004626",
    "type": "WHALE ALERT",
    "message": "Large ASK order detected: $107,844 on 'No' at 0.82\u00a2",
    "severity": "high",
    "market_question": "Will the Los Angeles Rams win Super Bowl 2026?",
    "market_slug": "will-the-los-angeles-rams-win-super-bowl-2026",
    "value": 107844.0,
    "price": 0.817,
    "size": 132000.0
  },
  {
    "id": "c802397d3b1f8ecb62a589af4edcc90a",
    "time": "10:44 UTC",
    "timestamp": "2026-01-17T10:44:41.002910",
    "type": "WHALE ALERT",
    "message": "Large ASK order detected: $609,541 on 'No' at 1.00\u00a2",
    "severity": "high",
    "market_question": "Will the Los Angeles Rams win Super Bowl 2026?",
    "market_slug": "will-the-los-angeles-rams-win-super-bowl-2026",
    "value": 609540.80904,
    "price": 0.999,
    "size": 610150.96
  },
  {
    "id": "8afb332cfeaf530549e971ec131dc48e",
    "time": "10:44 UTC",
    "timestamp": "2026-01-17T10:44:41.001840",
    "type": "WHALE ALERT",
    "message": "Large BID order detected: $40,021 on 'No' at 0.78\u00a2",
    "severity": "medium",
    "market_question": "Will the Los Angeles Rams win Super Bowl 2026?",
    "market_slug": "will-the-los-angeles-rams-win-super-bowl-2026",
    "value": 40021.212550000004,
    "price": 0.781,
    "size": 51243.55
  },
  {
    "id": "d9f4e64b6832f70b24021b1e667b2dea",
    "time": "10:44 UTC",
    "timestamp": "2026-01-17T10:44:41.000601",
    "type": "WHALE ALERT",
    "message": "Large BID order detected: $8,096 on 'No' at 0.77\u00a2",
    "severity": "medium",
    "market_question": "Will the Los Angeles Rams win Super Bowl 2026?",
    "market_slug": "will-the-los-angeles-rams-win-super-bowl-2026",
    "value": 8096.271000000001,
    "price": 0.771,
    "size": 10501.0
  },
  {
    "id": "0abc5f9509735c49c98b4905129a2bc7",
    "time": "10:44 UTC",
    "timestamp": "2026-01-17T10:44:40.999422",
    "type": "WHALE ALERT",
    "message": "Large BID order detected: $6,187 on 'No' at 0.77\u00a2",
    "severity": "medium",
    "market_question": "Will the Los Angeles Rams win Super Bowl 2026?",
    "market_slug": "will-the-los-angeles-rams-win-super-bowl-2026",
    "value": 6186.982,
    "price": 0.766,
    "size": 8077.0
  },
  {
    "id": "d4fea9d72d1697a3dc283f3d0eb6ba4c",
    "time": "10:44 UTC",
    "timestamp": "2026-01-17T10:44:40.824308",
    "type": "WHALE ALERT",
    "message": "Large ASK order detected: $11,222 on 'Yes' at 0.22\u00a2",
    "severity": "medium",
    "market_question": "Will the Los Angeles Rams win Super Bowl 2026?",
    "market_slug": "will-the-los-angeles-rams-win-super-bowl-2026",
    "value": 11222.33745,
    "price": 0.219,
    "size": 51243.55
  },
  {
    "id": "bcdde304665864bcf7d2f5806aa06ddc",
    "time": "10:44 UTC",
    "timestamp": "2026-01-17T10:44:40.822933",
    "type": "WHALE ALERT",
    "message": "Large BID order detected: $6,214 on 'Yes' at 0.20\u00a2",
    "severity": "medium",
    "market_question": "Will the Los Angeles Rams win Super Bowl 2026?",
    "market_slug": "will-the-los-angeles-rams-win-super-bowl-2026",
    "value": 6213.978,
    "price": 0.2,
    "size": 31069.89
  },
  {
    "id": "5d7512197dbcbf1c86ab61cd33c3bb4e",
    "time": "10:44 UTC",
    "timestamp": "2026-01-17T10:44:40.821909",
    "type": "WHALE ALERT",
    "message": "Large BID order detected: $11,797 on 'Yes' at 0.19\u00a2",
    "severity": "medium",
    "market_question": "Will the Los Angeles Rams win Super Bowl 2026?",
    "market_slug": "will-the-los-angeles-rams-win-super-bowl-2026",
    "value": 11797.140000000001,
    "price": 0.194,
    "size": 60810.0
  },
  {
    "id": "4ac90290a15b4246e422a51b83f930b9",
    "time": "10:44 UTC",
    "timestamp": "2026-01-17T10:44:40.820868",
    "type": "WHALE ALERT",
    "message": "Large BID order detected: $213,256 on 'Yes' at 0.19\u00a2",
    "severity": "high",
    "market_question": "Will the Los Angeles Rams win Super Bowl 2026?",
    "market_slug": "will-the-los-angeles-rams-win-super-bowl-2026",
    "value": 213256.315,
    "price": 0.193,
    "size": 1104955.0
  },
  {
    "id": "32e4a17b3226a751d5763a320d851a07",
    "time": "10:44 UTC",
    "timestamp": "2026-01-17T10:44:40.819701",
    "type": "WHALE ALERT",
    "message": "Large BID order detected: $24,156 on 'Yes' at 0.18\u00a2",
    "severity": "medium",
    "market_question": "Will the Los Angeles Rams win Super Bowl 2026?",
    "market_slug": "will-the-los-angeles-rams-win-super-bowl-2026",
    "value": 24156.0,
    "price": 0.183,
    "size": 132000.0
  },
  {
    "id": "9c1aa36736b9a711a004f1f23c3768dd",
    "time": "10:44 UTC",
    "timestamp": "2026-01-17T10:44:38.184234",
    "type": "WHALE ALERT",
    "message": "Large ASK order detected: $28,020 on 'No' at 0.93\u00a2",
    "severity": "medium",
    "market_question": "Will the Houston Texans win Super Bowl 2026?",
    "market_slug": "will-the-houston-texans-win-super-bowl-2026",
    "value": 28020.0,
    "price": 0.934,
    "size": 30000.0
  },
  {
    "id": "227ae2f8a0a3522e83920fd012ce7300",
    "time": "10:44 UTC",
    "timestamp": "2026-01-17T10:44:38.183163",
    "type": "WHALE ALERT",
    "message": "Large ASK order detected: $908,194 on 'No' at 1.00\u00a2",
    "severity": "high",
    "market_question": "Will the Houston Texans win Super Bowl 2026?",
    "market_slug": "will-the-houston-texans-win-super-bowl-2026",
    "value": 908194.1967000001,
    "price": 0.999,
    "size": 909103.3
  },
  {
    "id": "807a0fe28ff24541fdb41a1c8f10ec45",
    "time": "10:44 UTC",
    "timestamp": "2026-01-17T10:44:38.181964",
    "type": "WHALE ALERT",
    "message": "Large BID order detected: $22,398 on 'No' at 0.89\u00a2",
    "severity": "medium",
    "market_question": "Will the Houston Texans win Super Bowl 2026?",
    "market_slug": "will-the-houston-texans-win-super-bowl-2026",
    "value": 22398.12,
    "price": 0.892,
    "size": 25110.0
  },
  {
    "id": "57706a986ad99c914104e48d174711b7",
    "time": "10:44 UTC",
    "timestamp": "2026-01-17T10:44:36.802576",
    "type": "WHALE ALERT",
    "message": "Large ASK order detected: $51,908 on 'No' at 0.90\u00a2",
    "severity": "high",
    "market_question": "Will the Denver Broncos win Super Bowl 2026?",
    "market_slug": "will-the-denver-broncos-win-super-bowl-2026",
    "value": 51907.70712,
    "price": 0.904,
    "size": 57420.03
  },
  {
    "id": "7aa8a7b2c40cd1046bb8f7fd013e4cb0",
    "time": "10:44 UTC",
    "timestamp": "2026-01-17T10:44:36.801242",
    "type": "WHALE ALERT",
    "message": "Large ASK order detected: $91,957 on 'No' at 0.91\u00a2",
    "severity": "high",
    "market_question": "Will the Denver Broncos win Super Bowl 2026?",
    "market_slug": "will-the-denver-broncos-win-super-bowl-2026",
    "value": 91956.85995,
    "price": 0.905,
    "size": 101609.79
  },
  {
    "id": "6a8ab08facf488ea0ce65f75c87bca81",
    "time": "10:44 UTC",
    "timestamp": "2026-01-17T10:44:36.797592",
    "type": "WHALE ALERT",
    "message": "Large ASK order detected: $257,748 on 'No' at 0.91\u00a2",
    "severity": "high",
    "market_question": "Will the Denver Broncos win Super Bowl 2026?",
    "market_slug": "will-the-denver-broncos-win-super-bowl-2026",
    "value": 257748.0,
    "price": 0.914,
    "size": 282000.0
  }
]